P201_Functions/P201_Functions.py
P201_Functions/__init__.py
P201_Functions-1.0.dist-info/LICENSE.txt
P201_Functions-1.0.dist-info/METADATA
P201_Functions-1.0.dist-info/WHEEL
P201_Functions-1.0.dist-info/top_level.txt
P201_Functions-1.0.dist-info/RECORD
