Metadata-Version: 2.1
Name: P201-Functions
Version: 1.0
Summary: Fitting and Weighted Average Functions for Physics 201/202
Home-page: https://github.com/brash99/PhysicsLabs/blob/main/PHYS201L/JupyterNotebooks/P201_Functions.py
Author: Edward Brash
Author-email: edward.brash@cnu.edu
License: MIT
Platform: UNKNOWN
License-File: LICENSE.txt
Requires-Dist: numpy
Requires-Dist: matplotlib
Requires-Dist: scikit-learn
Requires-Dist: scipy
